autophot/__init__.py
autophot-1.0.0.dist-info/METADATA
autophot-1.0.0.dist-info/WHEEL
autophot-1.0.0.dist-info/entry_points.txt
autophot-1.0.0.dist-info/top_level.txt
autophot-1.0.0.dist-info/RECORD
