Metadata-Version: 2.1
Name: autophot
Version: 1.0.0
Summary: Sorry this has moved to: AstroPhot. Please run: pip install astrophot
Home-page: https://github.com/Autostronomy/AutoPhot
Author: Connor Stone
Author-email: connorstone628@gmail.com
License: GPL-3.0 license
Classifier: Intended Audience :: Science/Research
Classifier: License :: OSI Approved :: GNU General Public License v3 (GPLv3)
Classifier: Programming Language :: Python :: 3
Requires-Dist: numpy
